eas2cli/__init__.py
eas2cli/core.py
eas2cli/eas2cli.py
eas2cli/models.py
eas2cli-0.1.post2.dist-info/licenses/LICENSE
eas2cli-0.1.post2.dist-info/METADATA
eas2cli-0.1.post2.dist-info/WHEEL
eas2cli-0.1.post2.dist-info/entry_points.txt
eas2cli-0.1.post2.dist-info/top_level.txt
eas2cli-0.1.post2.dist-info/RECORD
