Metadata-Version: 2.4
Name: eas2cli
Version: 0.1.post2
Summary: eas2cli: A client to the EIDA Authentication System
Author-email: Javier Quinteros <javier@gfz.de>
License-Expression: GPL-3.0-or-later
Project-URL: Homepage, https://git.gfz-potsdam.de/javier/eas2cli
Project-URL: Issues, https://git.gfz-potsdam.de/javier/eas2cli/issues
Keywords: AAI,Authentication,EIDA,FDSN,Web Services
Classifier: Development Status :: 5 - Production/Stable
Classifier: Environment :: Console
Classifier: Framework :: Pydantic :: 2
Classifier: Intended Audience :: Science/Research
Classifier: Intended Audience :: End Users/Desktop
Classifier: Natural Language :: English
Classifier: Operating System :: POSIX :: Linux
Classifier: Operating System :: MacOS
Classifier: Programming Language :: Python :: 3
Classifier: Programming Language :: Python :: 3.10
Classifier: Programming Language :: Python :: 3.11
Classifier: Programming Language :: Python :: 3.12
Classifier: Topic :: Scientific/Engineering
Classifier: Topic :: Security
Classifier: Topic :: System :: Systems Administration :: Authentication/Directory
Requires-Python: >=3.10
License-File: LICENSE
Requires-Dist: pydantic>=2
Requires-Dist: click
Requires-Dist: PyJWT[crypto]
Dynamic: license-file
